gitlabcis/__init__.py
gitlabcis/__main__.py
gitlabcis/benchmarks/__init__.py
gitlabcis/benchmarks/artifacts_4/__init__.py
gitlabcis/benchmarks/artifacts_4/access_to_artifacts_4_2.py
gitlabcis/benchmarks/artifacts_4/origin_traceability_4_4.py
gitlabcis/benchmarks/artifacts_4/package_registries_4_3.py
gitlabcis/benchmarks/artifacts_4/verification_4_1.py
gitlabcis/benchmarks/build_pipelines_2/__init__.py
gitlabcis/benchmarks/build_pipelines_2/build_environment_2_1.py
gitlabcis/benchmarks/build_pipelines_2/build_worker_2_2.py
gitlabcis/benchmarks/build_pipelines_2/pipeline_instructions_2_3.py
gitlabcis/benchmarks/build_pipelines_2/pipeline_integrity_2_4.py
gitlabcis/benchmarks/dependencies_3/__init__.py
gitlabcis/benchmarks/dependencies_3/third_party_packages_3_1.py
gitlabcis/benchmarks/dependencies_3/validate_packages_3_2.py
gitlabcis/benchmarks/deployment_5/__init__.py
gitlabcis/benchmarks/deployment_5/deployment_configuration_5_1.py
gitlabcis/benchmarks/deployment_5/deployment_environment_5_2.py
gitlabcis/benchmarks/source_code_1/__init__.py
gitlabcis/benchmarks/source_code_1/code_changes_1_1.py
gitlabcis/benchmarks/source_code_1/code_risks_1_5.py
gitlabcis/benchmarks/source_code_1/contribution_access_1_3.py
gitlabcis/benchmarks/source_code_1/repository_management_1_2.py
gitlabcis/benchmarks/source_code_1/third_party_1_4.py
gitlabcis/cli/__init__.py
gitlabcis/cli/argsInput.py
gitlabcis/cli/auth.py
gitlabcis/cli/log.py
gitlabcis/cli/main.py
gitlabcis/cli/output.py
gitlabcis/recommendations/readme.md
gitlabcis/recommendations/template.yml
gitlabcis/recommendations/artifacts_4/readme.md
gitlabcis/recommendations/artifacts_4/access_to_artifacts_4_2/external_auth_server.yml
gitlabcis/recommendations/artifacts_4/access_to_artifacts_4_2/limit_artifact_uploaders.yml
gitlabcis/recommendations/artifacts_4/access_to_artifacts_4_2/limit_certifying_artifacts.yml
gitlabcis/recommendations/artifacts_4/access_to_artifacts_4_2/minimum_package_registry_admins.yml
gitlabcis-1.15.22.dist-info/licenses/LICENSE
gitlabcis-1.15.22.dist-info/METADATA
gitlabcis-1.15.22.dist-info/WHEEL
gitlabcis-1.15.22.dist-info/entry_points.txt
gitlabcis-1.15.22.dist-info/top_level.txt
gitlabcis-1.15.22.dist-info/RECORD
