Metadata-Version: 2.4
Name: gitlabcis
Version: 1.15.22
Summary: An automated tool that assesses the GitLab CIS benchmarks against a project.
Author-email: Nate Rosandich <nrosandich+gitlabcis@gitlab.com>, Neil McDonald <nmcdonald+gitlabcis@gitlab.com>, Mitra JozeNazemian <mjozenazemian+gitlabcis@gitlab.com>
License: MIT License
Project-URL: homepage, https://gitlab.com/gitlab-security-oss/cis/gitlabcis/
Project-URL: documentation, https://gitlab.com/gitlab-security-oss/cis/gitlabcis/-/tree/main/docs
Project-URL: issues, https://gitlab.com/gitlab-security-oss/cis/gitlabcis/-/issues
Project-URL: changelog, https://gitlab.com/gitlab-security-oss/cis/gitlabcis/-/tree/main/CHANGELOG.md
Project-URL: download, https://gitlab.com/gitlab-security-oss/cis/gitlabcis/-/releases
Keywords: GitLab Benchmarks,CIS Benchmarks,GitLab Hardening,GitLab Recommendations,GitLabcis,GitLab CIS Benchmarks,gitlabcis,GitLab,CIS,Benchmark Scanner,GitLab CIS Benchmark scanner,GitLab CIS
Classifier: Development Status :: 3 - Alpha
Classifier: Environment :: Console
Classifier: Intended Audience :: Information Technology
Classifier: Intended Audience :: System Administrators
Classifier: Intended Audience :: Developers
Classifier: Natural Language :: English
Classifier: License :: OSI Approved :: MIT License
Classifier: Operating System :: OS Independent
Classifier: Programming Language :: Python
Classifier: Programming Language :: Python :: 3
Classifier: Programming Language :: Python :: 3.10
Classifier: Programming Language :: Python :: 3.11
Classifier: Programming Language :: Python :: 3.12
Classifier: Programming Language :: Python :: 3 :: Only
Classifier: Topic :: Software Development :: Libraries :: Application Frameworks
Classifier: Topic :: Software Development :: Libraries :: Python Modules
Classifier: Topic :: System :: Benchmark
Classifier: Topic :: Security
Requires-Python: >=3.10
License-File: LICENSE
Requires-Dist: PyYAML==6.0.3
Requires-Dist: python-gitlab==6.5.0
Requires-Dist: tabulate==0.9.0
Requires-Dist: tqdm==4.67.1
Requires-Dist: defusedxml==0.7.1
Requires-Dist: python-dateutil==2.9.0.post0
Requires-Dist: gql==3.5.3
Provides-Extra: build
Requires-Dist: setuptools~=80.0; extra == "build"
Requires-Dist: wheel==0.45.1; extra == "build"
Requires-Dist: build==1.3.0; extra == "build"
Requires-Dist: setuptools-scm~=9.2.0; extra == "build"
Requires-Dist: twine==6.1.0; extra == "build"
Provides-Extra: test
Requires-Dist: pipdeptree==2.30.0; extra == "test"
Requires-Dist: pre-commit~=4.5.1; extra == "test"
Requires-Dist: pytest==8.4.2; extra == "test"
Requires-Dist: flake8~=7.3.0; extra == "test"
Requires-Dist: bandit==1.9.2; extra == "test"
Requires-Dist: yamllint==1.37.1; extra == "test"
Requires-Dist: pytest-cov==6.3.0; extra == "test"
Requires-Dist: coverage==7.13.1; extra == "test"
Requires-Dist: tox~=4.34.1; extra == "test"
Dynamic: license-file
